cursor_credits/__init__.py
cursor_credits/api.py
cursor_credits/auth.py
cursor_credits/cli.py
cursor_credits/display.py
cursor_credits/main.py
cursor_credits/paths.py
cursor_credits-0.2.0.dist-info/METADATA
cursor_credits-0.2.0.dist-info/WHEEL
cursor_credits-0.2.0.dist-info/entry_points.txt
cursor_credits-0.2.0.dist-info/licenses/LICENSE
cursor_credits-0.2.0.dist-info/RECORD
