Metadata-Version: 2.4
Name: cursor-credits
Version: 0.2.0
Summary: A clean, command-line tool to check your Cursor account usage credits
Project-URL: Homepage, https://github.com/CaptainCodeAU/cursor_credits
Project-URL: Repository, https://github.com/CaptainCodeAU/cursor_credits
Author-email: CaptainCodeAU <captain@example.com>
License: MIT
License-File: LICENSE
Classifier: License :: OSI Approved :: MIT License
Classifier: Operating System :: OS Independent
Classifier: Programming Language :: Python :: 3
Classifier: Programming Language :: Python :: 3.13
Requires-Python: <3.14,>=3.13
Requires-Dist: colorama
Requires-Dist: pyjwt
Requires-Dist: requests
Provides-Extra: dev
Requires-Dist: pytest; extra == 'dev'
Requires-Dist: pytest-cov; extra == 'dev'
Requires-Dist: ruff; extra == 'dev'
